ReactJishuZhanXilieJiaocheng/README.md
ReactJishuZhanXilieJiaocheng/__init__.py
ReactJishuZhanXilieJiaocheng/__main__.py
ReactJishuZhanXilieJiaocheng/file.epub
ReactJishuZhanXilieJiaocheng/index.html
ReactJishuZhanXilieJiaocheng/css/__init__.py
ReactJishuZhanXilieJiaocheng/css/annotations.css
ReactJishuZhanXilieJiaocheng/css/main.css
ReactJishuZhanXilieJiaocheng/css/normalize.css
ReactJishuZhanXilieJiaocheng/css/popup.css
ReactJishuZhanXilieJiaocheng/font/__init__.py
ReactJishuZhanXilieJiaocheng/font/fontello.eot
ReactJishuZhanXilieJiaocheng/font/fontello.svg
ReactJishuZhanXilieJiaocheng/font/fontello.ttf
ReactJishuZhanXilieJiaocheng/font/fontello.woff
ReactJishuZhanXilieJiaocheng/img/__init__.py
ReactJishuZhanXilieJiaocheng/img/annotator-glyph-sprite.png
ReactJishuZhanXilieJiaocheng/img/annotator-icon-sprite.png
ReactJishuZhanXilieJiaocheng/img/apple-touch-icon.png
ReactJishuZhanXilieJiaocheng/img/cancelfullscreen.png
ReactJishuZhanXilieJiaocheng/img/close.png
ReactJishuZhanXilieJiaocheng/img/fullscreen.png
ReactJishuZhanXilieJiaocheng/img/loader.gif
ReactJishuZhanXilieJiaocheng/img/menu-icon.png
ReactJishuZhanXilieJiaocheng/img/save.png
ReactJishuZhanXilieJiaocheng/img/saved.png
ReactJishuZhanXilieJiaocheng/img/settings-s.png
ReactJishuZhanXilieJiaocheng/img/settings.png
ReactJishuZhanXilieJiaocheng/img/star.png
ReactJishuZhanXilieJiaocheng/js/__init__.py
ReactJishuZhanXilieJiaocheng/js/epub.js
ReactJishuZhanXilieJiaocheng/js/epub.min.js
ReactJishuZhanXilieJiaocheng/js/epub.min.map
ReactJishuZhanXilieJiaocheng/js/hooks.min.js
ReactJishuZhanXilieJiaocheng/js/hooks.min.map
ReactJishuZhanXilieJiaocheng/js/reader.js
ReactJishuZhanXilieJiaocheng/js/reader.js.map
ReactJishuZhanXilieJiaocheng/js/reader.min.js
ReactJishuZhanXilieJiaocheng/js/reader.min.map
ReactJishuZhanXilieJiaocheng/js/hooks/__init__.py
ReactJishuZhanXilieJiaocheng/js/hooks/extensions/__init__.py
ReactJishuZhanXilieJiaocheng/js/hooks/extensions/highlight.js
react_jishu_zhan_xilie_jiaocheng-2024.3.2.0.dist-info/METADATA
react_jishu_zhan_xilie_jiaocheng-2024.3.2.0.dist-info/WHEEL
react_jishu_zhan_xilie_jiaocheng-2024.3.2.0.dist-info/entry_points.txt
react_jishu_zhan_xilie_jiaocheng-2024.3.2.0.dist-info/top_level.txt
react_jishu_zhan_xilie_jiaocheng-2024.3.2.0.dist-info/RECORD
